MANIFEST.in
README.md
setup.py
WorkshopMetadataExtract/WorkshopExplorer.py
WorkshopMetadataExtract/__init__.py
WorkshopMetadataExtract.egg-info/PKG-INFO
WorkshopMetadataExtract.egg-info/SOURCES.txt
WorkshopMetadataExtract.egg-info/dependency_links.txt
WorkshopMetadataExtract.egg-info/requires.txt
WorkshopMetadataExtract.egg-info/top_level.txt