Metadata-Version: 2.1
Name: WorkshopMetadataExtract
Version: 1.0.5
Summary: WME - Is a Python module that allows you to easily fetch and download workshop files from the Steam Workshop. This module makes use of the Steam API to retrieve information about workshop files, including their creators, file sizes, file URLs, and more. You can also download the workshop files and save them to your local machine using this module.
Home-page: https://github.com/IaVashik/WorkshopMetadataExtract
Author: laVashik
Author-email: lavash.assistant@gmail.com
License: UNKNOWN
Platform: UNKNOWN
Classifier: Development Status :: 5 - Production/Stable
Classifier: Intended Audience :: Developers
Classifier: License :: OSI Approved :: MIT License
Classifier: Operating System :: OS Independent
Classifier: Programming Language :: Python :: 3
Classifier: Programming Language :: Python :: 3.7
Classifier: Programming Language :: Python :: 3.8
Classifier: Programming Language :: Python :: 3.9
